[
    {
        "name": "Buy a new powerful computer",
        "date": 1521388111111,
        "status": "done",
        "mode": "none",
        "visible": true
    },
    {
        "name": "Buy a new powerful TV",
        "date": 1521388112222,
        "status": "done",
        "mode": "new",
        "visible": true
    },
    {
        "name": "Buy a new powerful car",
        "date": 1521388113333,
        "status": "done",
        "mode": "none",
        "visible": true
    },
    {
        "name": "Buy a new powerful car",
        "date": 1521388114444,
        "status": "new",
        "mode": "none",
        "visible": true
    }
]

